<?xml version = '1.0' encoding = 'UTF-8'?>
<FKIndexAssociation class="oracle.dbtools.crest.model.design.relational.FKIndexAssociation" directorySegmentName="seg_0" id="FEFFDAAF-039F-F259-47B1-CDD4DE1A38BC" containerWithKeyObject="00F84167-5B60-56A0-D276-7EFC8532E6E3" localFKIndex="8AA341BF-64AC-5776-D9CD-3E4731B3B846" name="fk_2116caaa389c7e4f8a65070af52">
<sourceDDLFile>AMEI_HOM.sql</sourceDDLFile>
<createdBy>andregutierres</createdBy>
<createdTime>2022-08-22 15:26:42 UTC</createdTime>
<ownerDesignName>AMORSAUDE</ownerDesignName>
<importedID>DF678F58-4A61-1564-9ADE-8A4C99B768A7</importedID>
<referredTableLongName>AMEI_APP_HOM.unidades</referredTableLongName>
<deleteRule>CASCADE</deleteRule>
<referredTableID>98845D87-ABB5-D449-EAC1-B5EA0DD0A184</referredTableID>
<keyObject>2C52E121-7019-C095-4D2D-FCF34E22B9AA</keyObject>
<referredKeyID>2C52E121-7019-C095-4D2D-FCF34E22B9AA</referredKeyID>
<mandatory>true</mandatory>
<refColNames>id</refColNames>
<transferable>true</transferable>
<rely>false</rely>
<columnDependencyConstraintGenerateInDDL>true</columnDependencyConstraintGenerateInDDL>
</FKIndexAssociation>